codegen_metrics/README.md
codegen_metrics/__init__.py
codegen_metrics/codebleu/__init__.py
codegen_metrics/codebleu/bleu_score.py
codegen_metrics/codebleu/codebleu.py
codegen_metrics/codebleu/graph_generator/__init__.py
codegen_metrics/codebleu/graph_generator/dataflowpass.py
codegen_metrics/codebleu/graph_generator/graphgenerator.py
codegen_metrics/codebleu/graph_generator/graphgenutils.py
codegen_metrics/codebleu/graph_generator/type_lattice_generator.py
codegen_metrics/codebleu/graph_generator/typeparsing/__init__.py
codegen_metrics/codebleu/graph_generator/typeparsing/aliasreplacement.py
codegen_metrics/codebleu/graph_generator/typeparsing/erasure.py
codegen_metrics/codebleu/graph_generator/typeparsing/inheritancerewrite.py
codegen_metrics/codebleu/graph_generator/typeparsing/nodes.py
codegen_metrics/codebleu/graph_generator/typeparsing/pruneannotations.py
codegen_metrics/codebleu/graph_generator/typeparsing/rewriterules/__init__.py
codegen_metrics/codebleu/graph_generator/typeparsing/rewriterules/removegenericwithany.py
codegen_metrics/codebleu/graph_generator/typeparsing/rewriterules/removerecursivegenerics.py
codegen_metrics/codebleu/graph_generator/typeparsing/rewriterules/removestandalones.py
codegen_metrics/codebleu/graph_generator/typeparsing/rewriterules/removeunionwithanys.py
codegen_metrics/codebleu/graph_generator/typeparsing/rewriterules/rewriterule.py
codegen_metrics/codebleu/graph_generator/typeparsing/rewriterulevisitor.py
codegen_metrics/codebleu/graph_generator/typeparsing/visitor.py
codegen_metrics/codebleu/typingRules.json
codegen_metrics/meteor/__init__.py
codegen_metrics/meteor/meteor.py
codegen_metrics/metrics.py
codegen_metrics/ruby/__init__.py
codegen_metrics/ruby/nx_graphs.py
codegen_metrics/ruby/similarity.py
codegen_metrics/ruby/test.py
codegen_metrics/ruby/typingRules.json
codegen_metrics/ruby/util.py
codegen_metrics/sacrebleu_code/__init__.py
codegen_metrics/sacrebleu_code/sacrebleu_methods/__init__.py
codegen_metrics-0.2.0.dist-info/LICENSE
codegen_metrics-0.2.0.dist-info/METADATA
codegen_metrics-0.2.0.dist-info/WHEEL
codegen_metrics-0.2.0.dist-info/RECORD
