Metadata-Version: 2.1
Name: codegen-metrics
Version: 0.2.0
Summary: Package for computation of code generation metrics
Home-page: https://github.com/JetBrains-Research/codegen-metrics-pip
License: MIT
Author: Egor Bogomolov
Author-email: egor.bogomolov@jetbrains.com
Requires-Python: >=3.9,<3.13
Classifier: License :: OSI Approved :: MIT License
Classifier: Programming Language :: Python :: 3
Classifier: Programming Language :: Python :: 3.9
Classifier: Programming Language :: Python :: 3.10
Classifier: Programming Language :: Python :: 3.11
Requires-Dist: appdirs (>=1.4.4,<2.0.0)
Requires-Dist: dpu-utils (>=0.6.1,<0.7.0)
Requires-Dist: editdistance (>=0.6.2,<0.7.0)
Requires-Dist: func-timeout (>=4.3.5,<5.0.0)
Requires-Dist: gitpython (>=3.1.36,<4.0.0)
Requires-Dist: networkx (>=3.1,<4.0)
Requires-Dist: nltk (>=3.8.1,<4.0.0)
Requires-Dist: rouge-score (>=0.1.2,<0.2.0)
Requires-Dist: scipy (>=1.11.2,<2.0.0)
Requires-Dist: tree-sitter (>=0.20.2,<0.21.0)
Requires-Dist: typed-ast (>=1.5.5,<2.0.0)
